scrapinghub_entrypoint_scrapy-0.17.6.dist-info/licenses/LICENSE
sh_scrapy/__init__.py
sh_scrapy/compat.py
sh_scrapy/crawl.py
sh_scrapy/diskquota.py
sh_scrapy/env.py
sh_scrapy/exceptions.py
sh_scrapy/extension.py
sh_scrapy/hsref.py
sh_scrapy/log.py
sh_scrapy/middlewares.py
sh_scrapy/settings.py
sh_scrapy/stats.py
sh_scrapy/utils.py
sh_scrapy/writer.py
sh_scrapy/commands/__init__.py
sh_scrapy/commands/shub_image_info.py
tests/__init__.py
tests/conftest.py
tests/test_command.py
tests/test_compat.py
tests/test_crawl.py
tests/test_diskquota.py
tests/test_env.py
tests/test_extension.py
tests/test_hsref.py
tests/test_log.py
tests/test_middlewares.py
tests/test_settings.py
tests/test_stats.py
tests/test_utils.py
tests/test_writer.py
tests/utils.py
scrapinghub_entrypoint_scrapy-0.17.6.dist-info/METADATA
scrapinghub_entrypoint_scrapy-0.17.6.dist-info/WHEEL
scrapinghub_entrypoint_scrapy-0.17.6.dist-info/entry_points.txt
scrapinghub_entrypoint_scrapy-0.17.6.dist-info/top_level.txt
scrapinghub_entrypoint_scrapy-0.17.6.dist-info/RECORD
